charm_json/__init__.py
charm_json/_main.py
charm_json-0.1.1.dist-info/METADATA
charm_json-0.1.1.dist-info/WHEEL
charm_json-0.1.1.dist-info/RECORD
