Metadata-Version: 2.1
Name: charm-json
Version: 0.1.1
Summary: 
Author: Carl Csaposs
Author-email: carl.csaposs@canonical.com
Requires-Python: >=3.8
Classifier: Programming Language :: Python :: 3
Classifier: Programming Language :: Python :: 3.8
Classifier: Programming Language :: Python :: 3.9
Classifier: Programming Language :: Python :: 3.10
Classifier: Programming Language :: Python :: 3.11
Classifier: Programming Language :: Python :: 3.12
Classifier: Programming Language :: Python :: 3.13
Requires-Dist: charm-api (>=0.1.1)
